
<translog>
		<formatter>
			<field>
				<expValue>(%Z)+3600</expValue>
				<fmtName>recvdTime</fmtName>
				<type>int</type>
			</field>
		</formatter>
	<!--
	<analyser>
		<outputs>
			<output>
				<fmtName>servTime</fmtName>
			</output>
			<output>
				<fmtName>servTime</fmtName>
				<expType>max</expType>
			</output>
			<output>
				<fmtName>status</fmtName>
			</output>
		</outputs>
		<type>consumed</type>
		<pace>1</pace>
	</analyser>
	-->
	<analyser>
		<outputs>
			<output>
				<fmtName>sm_cpu</fmtName>
			</output>
			<output>
				<fmtName>sm_mem</fmtName>
			</output>
			<output>
				<fmtName>sm_kmem</fmtName>
			</output>
			<output>
				<fmtName>sm_disk</fmtName>
			</output>
			<output>
				<fmtName>sm_web_cpu</fmtName>
			</output>
			<output>
				<fmtName>sm_web_requests</fmtName>
			</output>
			<output>
				<fmtName>sm_web_sessions</fmtName>
			</output>
			<output>
				<fmtName>sm_web_upstreams</fmtName>
			</output>
			<output>
				<fmtName>sm_perdisk</fmtName>
			</output>
		</outputs>
		<pace>2</pace>
	</analyser>
</translog>
